email_autoreply_bot/__init__.py
email_autoreply_bot/bot.py
email_autoreply_bot/cli.py
email_autoreply_bot/config.py
email_autoreply_bot/templates/default_config.yaml
email_autoreply_bot-0.1.4.dist-info/licenses/LICENSE
email_autoreply_bot-0.1.4.dist-info/METADATA
email_autoreply_bot-0.1.4.dist-info/WHEEL
email_autoreply_bot-0.1.4.dist-info/entry_points.txt
email_autoreply_bot-0.1.4.dist-info/top_level.txt
email_autoreply_bot-0.1.4.dist-info/RECORD
