Metadata-Version: 2.4
Name: email-autoreply-bot
Version: 0.1.4
Summary: An email auto-reply bot with configurable rules and templates
Author-email: Kumi <email-autoreply-bot@kumi.email>
License-Expression: MIT
Project-URL: Homepage, https://git.private.coffee/kumi/email-autoreply-bot
Project-URL: Bug Tracker, https://git.private.coffee/kumi/email-autoreply-bot/issues
Classifier: Programming Language :: Python :: 3
Classifier: Operating System :: OS Independent
Classifier: Development Status :: 4 - Beta
Requires-Python: >=3.7
License-File: LICENSE
Requires-Dist: pyyaml>=6.0
Requires-Dist: python-dateutil>=2.8.2
Requires-Dist: pytz>=2023.3
Requires-Dist: tzlocal>=5.0.1
Dynamic: license-file
